JunkFileOrganizer/__init__.py
JunkFileOrganizer-1.0.dist-info/LICENSE.txt
JunkFileOrganizer-1.0.dist-info/METADATA
JunkFileOrganizer-1.0.dist-info/WHEEL
JunkFileOrganizer-1.0.dist-info/top_level.txt
JunkFileOrganizer-1.0.dist-info/RECORD
