Metadata-Version: 2.1
Name: JunkFileOrganizer
Version: 1.0
Summary: This is a Junk File Organizer Module written in Python Language
Home-page: https://github.com/bikash-singh-au7/JunkFileOrganizer
Author: Bikash Kumar Singh
Author-email: UNKNOWN
License: UNKNOWN
Platform: UNKNOWN
